client_aic/ask.py
client_aic/authenticate.py
client_aic/get_cfg.py
client_aic/ppj.py
client_aic/config/core_config.py
client_aic/config/get_api_address.py
client_aic/config/get_creds.py
client_aic/config/get_tls.py
client_aic/models/core_job.py
client_aic/models/core_result_ai.py
client_aic/models/core_result_job.py
client_aic/models/core_search_result_ai.py
client_aic/models/core_user.py
client_aic/req/ai/create_ai_result.py
client_aic/req/ai/get_ai_result.py
client_aic/req/ai/run_job_ask.py
client_aic/req/ai/search_ai_results.py
client_aic/req/ai/update_ai_result.py
client_aic/req/auth/login.py
client_aic/req/job/get_job_result.py
client_aic/req/user/create_user.py
client_aic/req/user/get_user.py
client_aic/tls/utils.py
llama_client_aic-1.0.8.data/scripts/ask-llm.py
llama_client_aic-1.0.8.data/scripts/get-ai-result.py
llama_client_aic-1.0.8.data/scripts/review-answer.py
llama_client_aic-1.0.8.dist-info/LICENSE
llama_client_aic-1.0.8.dist-info/METADATA
llama_client_aic-1.0.8.dist-info/WHEEL
llama_client_aic-1.0.8.dist-info/top_level.txt
llama_client_aic-1.0.8.dist-info/RECORD
