Metadata-Version: 2.1
Name: llama-client-aic
Version: 1.0.8
Summary: python client for redten - a platform for building and testing distributed, self-hosted LLMs with native RAG and Reinforcement Learning with Human Feedback (RLHF) https://api.redten.io
Home-page: https://github.com/redten-ai/llama-client-aic
Author: redten-llamas
Author-email: info@redten.io
License: Apache 2.0
Keywords: artificial intelligence,deep learning,transformers,attention mechanism,reinforcement learning,human feedback
Platform: UNKNOWN
Classifier: Development Status :: 4 - Beta
Classifier: Intended Audience :: Developers
Classifier: Topic :: Scientific/Engineering :: Artificial Intelligence
Classifier: License :: OSI Approved :: MIT License
Classifier: Programming Language :: Python :: 3.10
License-File: LICENSE
Requires-Dist: argparse
Requires-Dist: flake8
Requires-Dist: pycodestyle
Requires-Dist: requests
Requires-Dist: ujson
Requires-Dist: uuid
